{
  "projects": [
    {
      "name": "SITE JJV",
      "budget": "9000",
      "category": {
        "id": "2",
        "name": "2"
      },
      "post": 0,
      "services": [],
      "id": 5
    },
    {
      "name": "INFRA ORACLE",
      "budget": "4000000",
      "category": {
        "id": "1",
        "name": "1"
      },
      "post": 0,
      "services": [
        {
          "name": "Serviços em nuvem",
          "cost": "1000000",
          "id": "bf0a6768-abe4-472f-b7c1-6a5500bc16ed"
        }
      ],
      "id": 6,
      "cost": null
    }
  ],
  "categories": [
    {
      "id": 1,
      "name": "Infra"
    },
    {
      "id": 2,
      "name": "Desenvolvimento"
    },
    {
      "id": 3,
      "name": "Design"
    },
    {
      "id": 4,
      "name": "Planejamento"
    }
  ]
}